odoo/addons/project_wise_task_colors/__init__.py
odoo/addons/project_wise_task_colors/__manifest__.py
odoo/addons/project_wise_task_colors/static/description/Banner.png
odoo/addons/project_wise_task_colors/static/description/icon.png
odoo/addons/project_wise_task_colors/static/description/index.html
odoo/addons/project_wise_task_colors/views/project_view.xml
odoo14_addon_project_wise_task_colors-14.0.0.0.1.dist-info/METADATA
odoo14_addon_project_wise_task_colors-14.0.0.0.1.dist-info/WHEEL
odoo14_addon_project_wise_task_colors-14.0.0.0.1.dist-info/top_level.txt
odoo14_addon_project_wise_task_colors-14.0.0.0.1.dist-info/RECORD
