Metadata-Version: 2.1
Name: odoo14-addon-project-wise-task-colors
Version: 14.0.0.0.1
Summary: Project Wise Tasks Color on Calendar View
Home-page: https://mediodconsulting.com/
Author: Mediod Consulting
License: LGPL-3
Platform: UNKNOWN
Classifier: Programming Language :: Python
Classifier: Framework :: Odoo
Classifier: Framework :: Odoo :: 14.0
Classifier: License :: OSI Approved :: GNU Lesser General Public License v3 (LGPLv3)
Requires-Python: >=3.6
Requires-Dist: odoo (<14.1dev,>=14.0a)
